yzal/__init__.py
yzal/py.typed
yzal-0.0.5.dist-info/LICENSE
yzal-0.0.5.dist-info/METADATA
yzal-0.0.5.dist-info/WHEEL
yzal-0.0.5.dist-info/top_level.txt
yzal-0.0.5.dist-info/RECORD
