Metadata-Version: 2.1
Name: yzal
Version: 0.0.5
Summary: Lazy evaluation for Python.
Home-page: https://github.com/ccarocean/yzal
Author: Michael R. Shannon
Author-email: mrshannon.aerospace@gmail.com
License: MIT
Platform: UNKNOWN
Classifier: Development Status :: 4 - Beta
Classifier: Intended Audience :: Developers
Classifier: License :: OSI Approved :: MIT License
Classifier: Programming Language :: Python
Classifier: Programming Language :: Python :: 3
Classifier: Programming Language :: Python :: 3.4
Classifier: Programming Language :: Python :: 3.5
Classifier: Programming Language :: Python :: 3.6
Classifier: Programming Language :: Python :: 3.7
Classifier: Topic :: Software Development :: Libraries
Requires-Dist: lazy-object-proxy
Requires-Dist: mypy ; python_version == "3.4"
